markwrap/__init__.py
markwrap/aws.py
markwrap/brew.py
markwrap/clamav.py
markwrap/conftest.py
markwrap/git.py
markwrap/gpg.py
markwrap/tar.py
markwrap/util/__init__.py
markwrap/util/check.py
markwrap/util/process.py
markwrap-0.0.20.dist-info/LICENSE
markwrap-0.0.20.dist-info/METADATA
markwrap-0.0.20.dist-info/WHEEL
markwrap-0.0.20.dist-info/top_level.txt
markwrap-0.0.20.dist-info/RECORD
