Metadata-Version: 2.1
Name: markwrap
Version: 0.0.20
Summary: Python wrappers around common dependencies
Home-page: https://github.com/willmarkley/markwrap
Author: Will Markley
License: UNKNOWN
Platform: UNKNOWN
Classifier: Intended Audience :: System Administrators
Classifier: License :: OSI Approved :: GNU General Public License v3 (GPLv3)
Classifier: Operating System :: Unix
Classifier: Programming Language :: Python :: 3.9
Classifier: Topic :: System
Classifier: Topic :: Software Development :: Libraries
Requires-Dist: boto3
Requires-Dist: python-gnupg
